pspringrestclient/__init__.py
pspringrestclient/mapping.py
pspringrestclient/regexresponsemapper.py
pspringrestclient/responsemapper.py
pspringrestclient/restclient.py
pspring_rest_client-0.2.3.dist-info/METADATA
pspring_rest_client-0.2.3.dist-info/WHEEL
pspring_rest_client-0.2.3.dist-info/top_level.txt
pspring_rest_client-0.2.3.dist-info/RECORD
