Metadata-Version: 2.1
Name: pspring-rest-client
Version: 0.2.3
Summary: A rest client for easier life
Home-page: https://github.com/vasudevan-palani/pspring-rest-client
Author: Vasudevan Palani
Author-email: vasudevan.palani@gmail.com
License: TBD
Requires-Dist: pspring (>=0.0.1)
